syndesi_drivers/__init__.py
syndesi_drivers/driver.py
syndesi_drivers/scpi_driver.py
syndesi_drivers/multimeters/__init__.py
syndesi_drivers/multimeters/keysight_344xxx.py
syndesi_drivers/multimeters/multimeters.py
syndesi_drivers/multimeters/siglent_sdm30x5.py
syndesi_drivers/oscilloscopes/__init__.py
syndesi_drivers/oscilloscopes/oscilloscopes.py
syndesi_drivers/oscilloscopes/siglent_sds1102cml.py
syndesi_drivers/ovens/__init__.py
syndesi_drivers/ovens/espec_sh242.py
syndesi_drivers/powersupplies/__init__.py
syndesi_drivers/powersupplies/powersupplies.py
syndesi_drivers/powersupplies/siglent_spd3303x.py
syndesi_drivers/powersupplies/tenma_72_13360.py
syndesi_drivers/sourcemeters/__init__.py
syndesi_drivers/sourcemeters/keithley_2450.py
syndesi_drivers/waveform_generators/__init__.py
syndesi_drivers/waveform_generators/keysight_33512B.py
syndesi_drivers/waveform_generators/keysight_edu33212a.py
syndesi_drivers/waveform_generators/tektronix_afg1022.py
syndesi_drivers-0.2.1.dist-info/METADATA
syndesi_drivers-0.2.1.dist-info/WHEEL
syndesi_drivers-0.2.1.dist-info/top_level.txt
syndesi_drivers-0.2.1.dist-info/RECORD
