Metadata-Version: 2.1
Name: syndesi-drivers
Version: 0.2.1
Summary: Syndesi drivers
Author: Sebastien Deriaz
Author-email: sebastien.deriaz1@gmail.com
Keywords: python,syndesi,drivers
Classifier: Development Status :: 3 - Alpha
Classifier: Intended Audience :: Education
Classifier: Programming Language :: Python :: 3
Classifier: Operating System :: Unix
Classifier: Operating System :: MacOS :: MacOS X
Classifier: Operating System :: Microsoft :: Windows
Requires-Dist: numpy
